{
  "generator-jhipster": {
    "promptValues": {
      "packageName": "br.com.payup.clientservice",
      "nativeLanguage": "en"
    },
    "jhipsterVersion": "4.9.0",
    "baseName": "clientservice",
    "packageName": "br.com.payup.clientservice",
    "packageFolder": "br/com/payup/clientservice",
    "serverPort": "8082",
    "authenticationType": "jwt",
    "hibernateCache": "hazelcast",
    "clusteredHttpSession": false,
    "websocket": false,
    "databaseType": "sql",
    "devDatabaseType": "mysql",
    "prodDatabaseType": "mysql",
    "searchEngine": false,
    "messageBroker": false,
    "serviceDiscoveryType": "eureka",
    "buildTool": "maven",
    "enableSocialSignIn": false,
    "enableSwaggerCodegen": false,
    "jwtSecretKey": "7b4ee9ded0317a66ead83aebc7016631a14b7171",
    "enableTranslation": true,
    "applicationType": "microservice",
    "testFrameworks": [
      "cucumber"
    ],
    "jhiPrefix": "jhi",
    "skipClient": true,
    "skipUserManagement": true,
    "nativeLanguage": "en",
    "languages": [
      "en",
      "pt-br"
    ],
    "clientPackageManager": "yarn"
  }
}